README.rst
setup.py
octohub/__init__.py
octohub/connection.py
octohub/exceptions.py
octohub/response.py
octohub/utils.py
octohub.egg-info/PKG-INFO
octohub.egg-info/SOURCES.txt
octohub.egg-info/dependency_links.txt
octohub.egg-info/top_level.txt