Metadata-Version: 2.1
Name: octohub
Version: 0.4
Summary: Low level Python and CLI interface to GitHub
Home-page: https://github.com/turnkeylinux/octohub
Author: Kirsten Hunter
Author-email: alon@turnkeylinux.org
License: GPLv3+
Classifier: License :: OSI Approved :: GNU General Public License v3 or later (GPLv3+)
